beetle_markdown/__init__.py
Beetle_Markdown-0.1.0.dist-info/WHEEL
Beetle_Markdown-0.1.0.dist-info/DESCRIPTION.rst
Beetle_Markdown-0.1.0.dist-info/RECORD
Beetle_Markdown-0.1.0.dist-info/METADATA
Beetle_Markdown-0.1.0.dist-info/metadata.json
Beetle_Markdown-0.1.0.dist-info/top_level.txt
