Metadata-Version: 2.0
Name: Beetle-Markdown
Version: 0.1.0
Summary: Makes Beetle do markdown
Home-page: https://github.com/cknv/beetle-markdown
Author: Esben Sonne
Author-email: esbensonne+code@gmail.com
License: MIT
Platform: UNKNOWN
Classifier: Environment :: Plugins
Classifier: Environment :: Console
Classifier: Development Status :: 3 - Alpha
Classifier: Intended Audience :: Developers
Classifier: License :: OSI Approved :: MIT License
Classifier: Programming Language :: Python :: 3
Classifier: Topic :: Text Processing :: Markup
Requires-Dist: Markdown
